{
  "totalHealth": 1335,
  "currentHealth": 1335,
  "userName": "e",
  "userClass": "Chicken Tender",
  "money": 116,
  "attack": 43,
  "defense": 69,
  "monstersKilled": 47,
  "itemList": [
    {
      "type": "miniRPG.Consumable",
      "data": {
        "healAmount": 28,
        "consumableValue": 0,
        "itemName": "Shrimp",
        "itemType": "Shrimp",
        "itemRequiredLevel": 1,
        "itemValue": 10
      }
    },
    {
      "type": "miniRPG.Smeltable",
      "data": {
        "name": "Ruby",
        "requiredLevelToSmith": 1,
        "value": 1,
        "itemName": "Ruby",
        "itemType": "Ruby",
        "itemRequiredLevel": 1,
        "itemValue": 1
      }
    },
    {
      "type": "miniRPG.Smeltable",
      "data": {
        "name": "Diamond",
        "requiredLevelToSmith": 1,
        "value": 1,
        "itemName": "Diamond",
        "itemType": "Diamond",
        "itemRequiredLevel": 1,
        "itemValue": 1
      }
    },
    {
      "type": "miniRPG.Smeltable",
      "data": {
        "name": "Sapphire",
        "requiredLevelToSmith": 1,
        "value": 1,
        "itemName": "Sapphire",
        "itemType": "Sapphire",
        "itemRequiredLevel": 1,
        "itemValue": 1
      }
    },
    {
      "type": "miniRPG.Smeltable",
      "data": {
        "name": "Sapphire",
        "requiredLevelToSmith": 1,
        "value": 1,
        "itemName": "Sapphire",
        "itemType": "Sapphire",
        "itemRequiredLevel": 1,
        "itemValue": 1
      }
    },
    {
      "type": "miniRPG.Smeltable",
      "data": {
        "name": "Sapphire",
        "requiredLevelToSmith": 1,
        "value": 1,
        "itemName": "Sapphire",
        "itemType": "Sapphire",
        "itemRequiredLevel": 1,
        "itemValue": 1
      }
    },
    {
      "type": "miniRPG.Smeltable",
      "data": {
        "name": "Sapphire",
        "requiredLevelToSmith": 1,
        "value": 1,
        "itemName": "Sapphire",
        "itemType": "Sapphire",
        "itemRequiredLevel": 1,
        "itemValue": 1
      }
    },
    {
      "type": "miniRPG.Smeltable",
      "data": {
        "name": "Sapphire",
        "requiredLevelToSmith": 1,
        "value": 1,
        "itemName": "Sapphire",
        "itemType": "Sapphire",
        "itemRequiredLevel": 1,
        "itemValue": 1
      }
    },
    {
      "type": "miniRPG.Smeltable",
      "data": {
        "name": "Sapphire",
        "requiredLevelToSmith": 1,
        "value": 1,
        "itemName": "Sapphire",
        "itemType": "Sapphire",
        "itemRequiredLevel": 1,
        "itemValue": 1
      }
    },
    {
      "type": "miniRPG.Smeltable",
      "data": {
        "name": "Sapphire",
        "requiredLevelToSmith": 1,
        "value": 1,
        "itemName": "Sapphire",
        "itemType": "Sapphire",
        "itemRequiredLevel": 1,
        "itemValue": 1
      }
    },
    {
      "type": "miniRPG.Smeltable",
      "data": {
        "name": "Sapphire",
        "requiredLevelToSmith": 1,
        "value": 1,
        "itemName": "Sapphire",
        "itemType": "Sapphire",
        "itemRequiredLevel": 1,
        "itemValue": 1
      }
    },
    {
      "type": "miniRPG.Smeltable",
      "data": {
        "name": "Sapphire",
        "requiredLevelToSmith": 1,
        "value": 1,
        "itemName": "Sapphire",
        "itemType": "Sapphire",
        "itemRequiredLevel": 1,
        "itemValue": 1
      }
    },
    {
      "type": "miniRPG.Smeltable",
      "data": {
        "name": "Sapphire",
        "requiredLevelToSmith": 1,
        "value": 1,
        "itemName": "Sapphire",
        "itemType": "Sapphire",
        "itemRequiredLevel": 1,
        "itemValue": 1
      }
    },
    {
      "type": "miniRPG.Smeltable",
      "data": {
        "name": "Sapphire",
        "requiredLevelToSmith": 1,
        "value": 1,
        "itemName": "Sapphire",
        "itemType": "Sapphire",
        "itemRequiredLevel": 1,
        "itemValue": 1
      }
    },
    {
      "type": "miniRPG.Smeltable",
      "data": {
        "name": "Bronze bar",
        "requiredLevelToSmith": 1,
        "value": 1,
        "itemName": "Bronze bar",
        "itemType": "Bronze bar",
        "itemRequiredLevel": 1,
        "itemValue": 1
      }
    },
    {
      "type": "miniRPG.Smeltable",
      "data": {
        "name": "Bronze bar",
        "requiredLevelToSmith": 1,
        "value": 1,
        "itemName": "Bronze bar",
        "itemType": "Bronze bar",
        "itemRequiredLevel": 1,
        "itemValue": 1
      }
    },
    {
      "type": "miniRPG.Smeltable",
      "data": {
        "name": "Bronze bar",
        "requiredLevelToSmith": 1,
        "value": 1,
        "itemName": "Bronze bar",
        "itemType": "Bronze bar",
        "itemRequiredLevel": 1,
        "itemValue": 1
      }
    },
    {
      "type": "miniRPG.Smeltable",
      "data": {
        "name": "Bronze bar",
        "requiredLevelToSmith": 1,
        "value": 1,
        "itemName": "Bronze bar",
        "itemType": "Bronze bar",
        "itemRequiredLevel": 1,
        "itemValue": 1
      }
    },
    {
      "type": "miniRPG.Smeltable",
      "data": {
        "name": "Bronze bar",
        "requiredLevelToSmith": 1,
        "value": 1,
        "itemName": "Bronze bar",
        "itemType": "Bronze bar",
        "itemRequiredLevel": 1,
        "itemValue": 1
      }
    },
    {
      "type": "miniRPG.Weapon",
      "data": {
        "attackBoost": 1,
        "weaponRequiredLevel": 0,
        "weaponValue": 0,
        "itemName": "Bronze sword",
        "itemType": "sword",
        "itemRequiredLevel": 1,
        "itemValue": 50
      }
    },
    {
      "type": "miniRPG.Consumable",
      "data": {
        "healAmount": 57,
        "consumableValue": 0,
        "itemName": "Shrimp",
        "itemType": "Shrimp",
        "itemRequiredLevel": 1,
        "itemValue": 10
      }
    },
    {
      "type": "miniRPG.Consumable",
      "data": {
        "healAmount": 57,
        "consumableValue": 0,
        "itemName": "Shrimp",
        "itemType": "Shrimp",
        "itemRequiredLevel": 1,
        "itemValue": 10
      }
    },
    {
      "type": "miniRPG.Consumable",
      "data": {
        "healAmount": 57,
        "consumableValue": 0,
        "itemName": "Shrimp",
        "itemType": "Shrimp",
        "itemRequiredLevel": 1,
        "itemValue": 10
      }
    },
    {
      "type": "miniRPG.Cookable",
      "data": {
        "cookableName": "Raw Chicken",
        "cookableXP": 150,
        "cookableLevelRequired": 5,
        "chanceToCook": 80,
        "newItem": {
          "type": "miniRPG.Consumable",
          "data": {
            "healAmount": 158,
            "consumableValue": 0,
            "itemName": "Chicken",
            "itemType": "Chicken",
            "itemRequiredLevel": 1,
            "itemValue": 20
          }
        },
        "cookableValue": 5,
        "userHealth": 793,
        "itemName": "Raw Chicken",
        "itemType": "Raw Chicken",
        "itemRequiredLevel": 5,
        "itemValue": 5
      }
    },
    {
      "type": "miniRPG.Cookable",
      "data": {
        "cookableName": "Raw Chicken",
        "cookableXP": 150,
        "cookableLevelRequired": 5,
        "chanceToCook": 80,
        "newItem": {
          "type": "miniRPG.Consumable",
          "data": {
            "healAmount": 158,
            "consumableValue": 0,
            "itemName": "Chicken",
            "itemType": "Chicken",
            "itemRequiredLevel": 1,
            "itemValue": 20
          }
        },
        "cookableValue": 5,
        "userHealth": 793,
        "itemName": "Raw Chicken",
        "itemType": "Raw Chicken",
        "itemRequiredLevel": 5,
        "itemValue": 5
      }
    },
    {
      "type": "miniRPG.Cookable",
      "data": {
        "cookableName": "Raw Chicken",
        "cookableXP": 150,
        "cookableLevelRequired": 5,
        "chanceToCook": 80,
        "newItem": {
          "type": "miniRPG.Consumable",
          "data": {
            "healAmount": 158,
            "consumableValue": 0,
            "itemName": "Chicken",
            "itemType": "Chicken",
            "itemRequiredLevel": 1,
            "itemValue": 20
          }
        },
        "cookableValue": 5,
        "userHealth": 793,
        "itemName": "Raw Chicken",
        "itemType": "Raw Chicken",
        "itemRequiredLevel": 5,
        "itemValue": 5
      }
    },
    {
      "type": "miniRPG.Smeltable",
      "data": {
        "name": "Sapphire",
        "requiredLevelToSmith": 1,
        "value": 1,
        "itemName": "Sapphire",
        "itemType": "Sapphire",
        "itemRequiredLevel": 1,
        "itemValue": 1
      }
    },
    {
      "type": "miniRPG.Smeltable",
      "data": {
        "name": "Ruby",
        "requiredLevelToSmith": 1,
        "value": 1,
        "itemName": "Ruby",
        "itemType": "Ruby",
        "itemRequiredLevel": 1,
        "itemValue": 1
      }
    },
    {
      "type": "miniRPG.Cookable",
      "data": {
        "cookableName": "Raw Beef",
        "cookableXP": 600,
        "cookableLevelRequired": 15,
        "chanceToCook": 0,
        "newItem": {
          "type": "miniRPG.Consumable",
          "data": {
            "healAmount": 333,
            "consumableValue": 0,
            "itemName": "Beef",
            "itemType": "Beef",
            "itemRequiredLevel": 1,
            "itemValue": 30
          }
        },
        "cookableValue": 5,
        "userHealth": 1110,
        "itemName": "Raw Beef",
        "itemType": "Raw Beef",
        "itemRequiredLevel": 15,
        "itemValue": 5
      }
    },
    {
      "type": "miniRPG.Consumable",
      "data": {
        "healAmount": 111,
        "consumableValue": 0,
        "itemName": "Shrimp",
        "itemType": "Shrimp",
        "itemRequiredLevel": 1,
        "itemValue": 10
      }
    },
    {
      "type": "miniRPG.Consumable",
      "data": {
        "healAmount": 111,
        "consumableValue": 0,
        "itemName": "Shrimp",
        "itemType": "Shrimp",
        "itemRequiredLevel": 1,
        "itemValue": 10
      }
    },
    {
      "type": "miniRPG.Consumable",
      "data": {
        "healAmount": 111,
        "consumableValue": 0,
        "itemName": "Shrimp",
        "itemType": "Shrimp",
        "itemRequiredLevel": 1,
        "itemValue": 10
      }
    },
    {
      "type": "miniRPG.Consumable",
      "data": {
        "healAmount": 111,
        "consumableValue": 0,
        "itemName": "Shrimp",
        "itemType": "Shrimp",
        "itemRequiredLevel": 1,
        "itemValue": 10
      }
    },
    {
      "type": "miniRPG.Consumable",
      "data": {
        "healAmount": 111,
        "consumableValue": 0,
        "itemName": "Shrimp",
        "itemType": "Shrimp",
        "itemRequiredLevel": 1,
        "itemValue": 10
      }
    },
    {
      "type": "miniRPG.Consumable",
      "data": {
        "healAmount": 111,
        "consumableValue": 0,
        "itemName": "Shrimp",
        "itemType": "Shrimp",
        "itemRequiredLevel": 1,
        "itemValue": 10
      }
    },
    {
      "type": "miniRPG.Consumable",
      "data": {
        "healAmount": 111,
        "consumableValue": 0,
        "itemName": "Shrimp",
        "itemType": "Shrimp",
        "itemRequiredLevel": 1,
        "itemValue": 10
      }
    },
    {
      "type": "miniRPG.Consumable",
      "data": {
        "healAmount": 111,
        "consumableValue": 0,
        "itemName": "Shrimp",
        "itemType": "Shrimp",
        "itemRequiredLevel": 1,
        "itemValue": 10
      }
    },
    {
      "type": "miniRPG.Consumable",
      "data": {
        "healAmount": 111,
        "consumableValue": 0,
        "itemName": "Shrimp",
        "itemType": "Shrimp",
        "itemRequiredLevel": 1,
        "itemValue": 10
      }
    },
    {
      "type": "miniRPG.Consumable",
      "data": {
        "healAmount": 111,
        "consumableValue": 0,
        "itemName": "Shrimp",
        "itemType": "Shrimp",
        "itemRequiredLevel": 1,
        "itemValue": 10
      }
    },
    {
      "type": "miniRPG.Consumable",
      "data": {
        "healAmount": 111,
        "consumableValue": 0,
        "itemName": "Shrimp",
        "itemType": "Shrimp",
        "itemRequiredLevel": 1,
        "itemValue": 10
      }
    },
    {
      "type": "miniRPG.Consumable",
      "data": {
        "healAmount": 111,
        "consumableValue": 0,
        "itemName": "Shrimp",
        "itemType": "Shrimp",
        "itemRequiredLevel": 1,
        "itemValue": 10
      }
    },
    {
      "type": "miniRPG.Consumable",
      "data": {
        "healAmount": 111,
        "consumableValue": 0,
        "itemName": "Shrimp",
        "itemType": "Shrimp",
        "itemRequiredLevel": 1,
        "itemValue": 10
      }
    },
    {
      "type": "miniRPG.Consumable",
      "data": {
        "healAmount": 111,
        "consumableValue": 0,
        "itemName": "Shrimp",
        "itemType": "Shrimp",
        "itemRequiredLevel": 1,
        "itemValue": 10
      }
    },
    {
      "type": "miniRPG.Consumable",
      "data": {
        "healAmount": 111,
        "consumableValue": 0,
        "itemName": "Shrimp",
        "itemType": "Shrimp",
        "itemRequiredLevel": 1,
        "itemValue": 10
      }
    },
    {
      "type": "miniRPG.Consumable",
      "data": {
        "healAmount": 111,
        "consumableValue": 0,
        "itemName": "Shrimp",
        "itemType": "Shrimp",
        "itemRequiredLevel": 1,
        "itemValue": 10
      }
    },
    {
      "type": "miniRPG.Consumable",
      "data": {
        "healAmount": 111,
        "consumableValue": 0,
        "itemName": "Shrimp",
        "itemType": "Shrimp",
        "itemRequiredLevel": 1,
        "itemValue": 10
      }
    },
    {
      "type": "miniRPG.Consumable",
      "data": {
        "healAmount": 111,
        "consumableValue": 0,
        "itemName": "Shrimp",
        "itemType": "Shrimp",
        "itemRequiredLevel": 1,
        "itemValue": 10
      }
    },
    {
      "type": "miniRPG.Consumable",
      "data": {
        "healAmount": 111,
        "consumableValue": 0,
        "itemName": "Shrimp",
        "itemType": "Shrimp",
        "itemRequiredLevel": 1,
        "itemValue": 10
      }
    },
    {
      "type": "miniRPG.Consumable",
      "data": {
        "healAmount": 111,
        "consumableValue": 0,
        "itemName": "Shrimp",
        "itemType": "Shrimp",
        "itemRequiredLevel": 1,
        "itemValue": 10
      }
    },
    {
      "type": "miniRPG.Consumable",
      "data": {
        "healAmount": 111,
        "consumableValue": 0,
        "itemName": "Shrimp",
        "itemType": "Shrimp",
        "itemRequiredLevel": 1,
        "itemValue": 10
      }
    },
    {
      "type": "miniRPG.Consumable",
      "data": {
        "healAmount": 111,
        "consumableValue": 0,
        "itemName": "Shrimp",
        "itemType": "Shrimp",
        "itemRequiredLevel": 1,
        "itemValue": 10
      }
    },
    {
      "type": "miniRPG.Consumable",
      "data": {
        "healAmount": 111,
        "consumableValue": 0,
        "itemName": "Shrimp",
        "itemType": "Shrimp",
        "itemRequiredLevel": 1,
        "itemValue": 10
      }
    },
    {
      "type": "miniRPG.Consumable",
      "data": {
        "healAmount": 111,
        "consumableValue": 0,
        "itemName": "Shrimp",
        "itemType": "Shrimp",
        "itemRequiredLevel": 1,
        "itemValue": 10
      }
    },
    {
      "type": "miniRPG.Consumable",
      "data": {
        "healAmount": 111,
        "consumableValue": 0,
        "itemName": "Shrimp",
        "itemType": "Shrimp",
        "itemRequiredLevel": 1,
        "itemValue": 10
      }
    },
    {
      "type": "miniRPG.Consumable",
      "data": {
        "healAmount": 111,
        "consumableValue": 0,
        "itemName": "Shrimp",
        "itemType": "Shrimp",
        "itemRequiredLevel": 1,
        "itemValue": 10
      }
    },
    {
      "type": "miniRPG.Consumable",
      "data": {
        "healAmount": 111,
        "consumableValue": 0,
        "itemName": "Shrimp",
        "itemType": "Shrimp",
        "itemRequiredLevel": 1,
        "itemValue": 10
      }
    },
    {
      "type": "miniRPG.Consumable",
      "data": {
        "healAmount": 111,
        "consumableValue": 0,
        "itemName": "Shrimp",
        "itemType": "Shrimp",
        "itemRequiredLevel": 1,
        "itemValue": 10
      }
    },
    {
      "type": "miniRPG.Consumable",
      "data": {
        "healAmount": 111,
        "consumableValue": 0,
        "itemName": "Shrimp",
        "itemType": "Shrimp",
        "itemRequiredLevel": 1,
        "itemValue": 10
      }
    },
    {
      "type": "miniRPG.Consumable",
      "data": {
        "healAmount": 111,
        "consumableValue": 0,
        "itemName": "Shrimp",
        "itemType": "Shrimp",
        "itemRequiredLevel": 1,
        "itemValue": 10
      }
    },
    {
      "type": "miniRPG.Consumable",
      "data": {
        "healAmount": 111,
        "consumableValue": 0,
        "itemName": "Shrimp",
        "itemType": "Shrimp",
        "itemRequiredLevel": 1,
        "itemValue": 10
      }
    },
    {
      "type": "miniRPG.Consumable",
      "data": {
        "healAmount": 79,
        "consumableValue": 0,
        "itemName": "Fish",
        "itemType": "Fish",
        "itemRequiredLevel": 1,
        "itemValue": 15
      }
    },
    {
      "type": "miniRPG.Consumable",
      "data": {
        "healAmount": 111,
        "consumableValue": 0,
        "itemName": "Fish",
        "itemType": "Fish",
        "itemRequiredLevel": 1,
        "itemValue": 15
      }
    },
    {
      "type": "miniRPG.Consumable",
      "data": {
        "healAmount": 111,
        "consumableValue": 0,
        "itemName": "Fish",
        "itemType": "Fish",
        "itemRequiredLevel": 1,
        "itemValue": 15
      }
    },
    {
      "type": "miniRPG.Consumable",
      "data": {
        "healAmount": 111,
        "consumableValue": 0,
        "itemName": "Fish",
        "itemType": "Fish",
        "itemRequiredLevel": 1,
        "itemValue": 15
      }
    },
    {
      "type": "miniRPG.Consumable",
      "data": {
        "healAmount": 111,
        "consumableValue": 0,
        "itemName": "Fish",
        "itemType": "Fish",
        "itemRequiredLevel": 1,
        "itemValue": 15
      }
    },
    {
      "type": "miniRPG.Consumable",
      "data": {
        "healAmount": 55,
        "consumableValue": 0,
        "itemName": "Potato",
        "itemType": "Potato",
        "itemRequiredLevel": 1,
        "itemValue": 1
      }
    },
    {
      "type": "miniRPG.Consumable",
      "data": {
        "healAmount": 111,
        "consumableValue": 0,
        "itemName": "Shrimp",
        "itemType": "Shrimp",
        "itemRequiredLevel": 1,
        "itemValue": 10
      }
    },
    {
      "type": "miniRPG.Consumable",
      "data": {
        "healAmount": 111,
        "consumableValue": 0,
        "itemName": "Shrimp",
        "itemType": "Shrimp",
        "itemRequiredLevel": 1,
        "itemValue": 10
      }
    },
    {
      "type": "miniRPG.Consumable",
      "data": {
        "healAmount": 111,
        "consumableValue": 0,
        "itemName": "Shrimp",
        "itemType": "Shrimp",
        "itemRequiredLevel": 1,
        "itemValue": 10
      }
    },
    {
      "type": "miniRPG.Consumable",
      "data": {
        "healAmount": 111,
        "consumableValue": 0,
        "itemName": "Shrimp",
        "itemType": "Shrimp",
        "itemRequiredLevel": 1,
        "itemValue": 10
      }
    },
    {
      "type": "miniRPG.Consumable",
      "data": {
        "healAmount": 111,
        "consumableValue": 0,
        "itemName": "Shrimp",
        "itemType": "Shrimp",
        "itemRequiredLevel": 1,
        "itemValue": 10
      }
    },
    {
      "type": "miniRPG.Consumable",
      "data": {
        "healAmount": 111,
        "consumableValue": 0,
        "itemName": "Shrimp",
        "itemType": "Shrimp",
        "itemRequiredLevel": 1,
        "itemValue": 10
      }
    },
    {
      "type": "miniRPG.Consumable",
      "data": {
        "healAmount": 111,
        "consumableValue": 0,
        "itemName": "Shrimp",
        "itemType": "Shrimp",
        "itemRequiredLevel": 1,
        "itemValue": 10
      }
    },
    {
      "type": "miniRPG.Consumable",
      "data": {
        "healAmount": 111,
        "consumableValue": 0,
        "itemName": "Shrimp",
        "itemType": "Shrimp",
        "itemRequiredLevel": 1,
        "itemValue": 10
      }
    },
    {
      "type": "miniRPG.Consumable",
      "data": {
        "healAmount": 111,
        "consumableValue": 0,
        "itemName": "Shrimp",
        "itemType": "Shrimp",
        "itemRequiredLevel": 1,
        "itemValue": 10
      }
    },
    {
      "type": "miniRPG.Consumable",
      "data": {
        "healAmount": 111,
        "consumableValue": 0,
        "itemName": "Shrimp",
        "itemType": "Shrimp",
        "itemRequiredLevel": 1,
        "itemValue": 10
      }
    },
    {
      "type": "miniRPG.Consumable",
      "data": {
        "healAmount": 111,
        "consumableValue": 0,
        "itemName": "Shrimp",
        "itemType": "Shrimp",
        "itemRequiredLevel": 1,
        "itemValue": 10
      }
    },
    {
      "type": "miniRPG.Consumable",
      "data": {
        "healAmount": 111,
        "consumableValue": 0,
        "itemName": "Shrimp",
        "itemType": "Shrimp",
        "itemRequiredLevel": 1,
        "itemValue": 10
      }
    },
    {
      "type": "miniRPG.Consumable",
      "data": {
        "healAmount": 111,
        "consumableValue": 0,
        "itemName": "Shrimp",
        "itemType": "Shrimp",
        "itemRequiredLevel": 1,
        "itemValue": 10
      }
    },
    {
      "type": "miniRPG.Consumable",
      "data": {
        "healAmount": 111,
        "consumableValue": 0,
        "itemName": "Shrimp",
        "itemType": "Shrimp",
        "itemRequiredLevel": 1,
        "itemValue": 10
      }
    },
    {
      "type": "miniRPG.Consumable",
      "data": {
        "healAmount": 111,
        "consumableValue": 0,
        "itemName": "Shrimp",
        "itemType": "Shrimp",
        "itemRequiredLevel": 1,
        "itemValue": 10
      }
    },
    {
      "type": "miniRPG.Consumable",
      "data": {
        "healAmount": 111,
        "consumableValue": 0,
        "itemName": "Shrimp",
        "itemType": "Shrimp",
        "itemRequiredLevel": 1,
        "itemValue": 10
      }
    },
    {
      "type": "miniRPG.Consumable",
      "data": {
        "healAmount": 111,
        "consumableValue": 0,
        "itemName": "Shrimp",
        "itemType": "Shrimp",
        "itemRequiredLevel": 1,
        "itemValue": 10
      }
    },
    {
      "type": "miniRPG.Consumable",
      "data": {
        "healAmount": 111,
        "consumableValue": 0,
        "itemName": "Shrimp",
        "itemType": "Shrimp",
        "itemRequiredLevel": 1,
        "itemValue": 10
      }
    },
    {
      "type": "miniRPG.Consumable",
      "data": {
        "healAmount": 111,
        "consumableValue": 0,
        "itemName": "Fish",
        "itemType": "Fish",
        "itemRequiredLevel": 1,
        "itemValue": 15
      }
    },
    {
      "type": "miniRPG.Consumable",
      "data": {
        "healAmount": 111,
        "consumableValue": 0,
        "itemName": "Fish",
        "itemType": "Fish",
        "itemRequiredLevel": 1,
        "itemValue": 15
      }
    },
    {
      "type": "miniRPG.Consumable",
      "data": {
        "healAmount": 111,
        "consumableValue": 0,
        "itemName": "Fish",
        "itemType": "Fish",
        "itemRequiredLevel": 1,
        "itemValue": 15
      }
    },
    {
      "type": "miniRPG.Consumable",
      "data": {
        "healAmount": 111,
        "consumableValue": 0,
        "itemName": "Fish",
        "itemType": "Fish",
        "itemRequiredLevel": 1,
        "itemValue": 15
      }
    },
    {
      "type": "miniRPG.Consumable",
      "data": {
        "healAmount": 111,
        "consumableValue": 0,
        "itemName": "Fish",
        "itemType": "Fish",
        "itemRequiredLevel": 1,
        "itemValue": 15
      }
    },
    {
      "type": "miniRPG.Consumable",
      "data": {
        "healAmount": 111,
        "consumableValue": 0,
        "itemName": "Fish",
        "itemType": "Fish",
        "itemRequiredLevel": 1,
        "itemValue": 15
      }
    },
    {
      "type": "miniRPG.Consumable",
      "data": {
        "healAmount": 111,
        "consumableValue": 0,
        "itemName": "Fish",
        "itemType": "Fish",
        "itemRequiredLevel": 1,
        "itemValue": 15
      }
    },
    {
      "type": "miniRPG.Consumable",
      "data": {
        "healAmount": 111,
        "consumableValue": 0,
        "itemName": "Fish",
        "itemType": "Fish",
        "itemRequiredLevel": 1,
        "itemValue": 15
      }
    },
    {
      "type": "miniRPG.Consumable",
      "data": {
        "healAmount": 111,
        "consumableValue": 0,
        "itemName": "Fish",
        "itemType": "Fish",
        "itemRequiredLevel": 1,
        "itemValue": 15
      }
    },
    {
      "type": "miniRPG.Consumable",
      "data": {
        "healAmount": 333,
        "consumableValue": 0,
        "itemName": "Lobster",
        "itemType": "Lobster",
        "itemRequiredLevel": 1,
        "itemValue": 30
      }
    },
    {
      "type": "miniRPG.Consumable",
      "data": {
        "healAmount": 333,
        "consumableValue": 0,
        "itemName": "Lobster",
        "itemType": "Lobster",
        "itemRequiredLevel": 1,
        "itemValue": 30
      }
    },
    {
      "type": "miniRPG.Consumable",
      "data": {
        "healAmount": 333,
        "consumableValue": 0,
        "itemName": "Lobster",
        "itemType": "Lobster",
        "itemRequiredLevel": 1,
        "itemValue": 30
      }
    },
    {
      "type": "miniRPG.Consumable",
      "data": {
        "healAmount": 333,
        "consumableValue": 0,
        "itemName": "Lobster",
        "itemType": "Lobster",
        "itemRequiredLevel": 1,
        "itemValue": 30
      }
    },
    {
      "type": "miniRPG.Consumable",
      "data": {
        "healAmount": 333,
        "consumableValue": 0,
        "itemName": "Lobster",
        "itemType": "Lobster",
        "itemRequiredLevel": 1,
        "itemValue": 30
      }
    },
    {
      "type": "miniRPG.Consumable",
      "data": {
        "healAmount": 333,
        "consumableValue": 0,
        "itemName": "Lobster",
        "itemType": "Lobster",
        "itemRequiredLevel": 1,
        "itemValue": 30
      }
    },
    {
      "type": "miniRPG.Consumable",
      "data": {
        "healAmount": 333,
        "consumableValue": 0,
        "itemName": "Lobster",
        "itemType": "Lobster",
        "itemRequiredLevel": 1,
        "itemValue": 30
      }
    },
    {
      "type": "miniRPG.Consumable",
      "data": {
        "healAmount": 333,
        "consumableValue": 0,
        "itemName": "Lobster",
        "itemType": "Lobster",
        "itemRequiredLevel": 1,
        "itemValue": 30
      }
    },
    {
      "type": "miniRPG.Consumable",
      "data": {
        "healAmount": 333,
        "consumableValue": 0,
        "itemName": "Lobster",
        "itemType": "Lobster",
        "itemRequiredLevel": 1,
        "itemValue": 30
      }
    },
    {
      "type": "miniRPG.Consumable",
      "data": {
        "healAmount": 333,
        "consumableValue": 0,
        "itemName": "Lobster",
        "itemType": "Lobster",
        "itemRequiredLevel": 1,
        "itemValue": 30
      }
    },
    {
      "type": "miniRPG.Consumable",
      "data": {
        "healAmount": 333,
        "consumableValue": 0,
        "itemName": "Lobster",
        "itemType": "Lobster",
        "itemRequiredLevel": 1,
        "itemValue": 30
      }
    },
    {
      "type": "miniRPG.Smeltable",
      "data": {
        "name": "Emerald",
        "requiredLevelToSmith": 1,
        "value": 1,
        "itemName": "Emerald",
        "itemType": "Emerald",
        "itemRequiredLevel": 1,
        "itemValue": 1
      }
    },
    {
      "type": "miniRPG.Smeltable",
      "data": {
        "name": "Ruby",
        "requiredLevelToSmith": 1,
        "value": 1,
        "itemName": "Ruby",
        "itemType": "Ruby",
        "itemRequiredLevel": 1,
        "itemValue": 1
      }
    },
    {
      "type": "miniRPG.Smeltable",
      "data": {
        "name": "Bronze bar",
        "requiredLevelToSmith": 1,
        "value": 1,
        "itemName": "Bronze bar",
        "itemType": "Bronze bar",
        "itemRequiredLevel": 1,
        "itemValue": 1
      }
    },
    {
      "type": "miniRPG.Smeltable",
      "data": {
        "name": "Bronze bar",
        "requiredLevelToSmith": 1,
        "value": 1,
        "itemName": "Bronze bar",
        "itemType": "Bronze bar",
        "itemRequiredLevel": 1,
        "itemValue": 1
      }
    },
    {
      "type": "miniRPG.Smeltable",
      "data": {
        "name": "Bronze bar",
        "requiredLevelToSmith": 1,
        "value": 1,
        "itemName": "Bronze bar",
        "itemType": "Bronze bar",
        "itemRequiredLevel": 1,
        "itemValue": 1
      }
    },
    {
      "type": "miniRPG.Smeltable",
      "data": {
        "name": "Bronze bar",
        "requiredLevelToSmith": 1,
        "value": 1,
        "itemName": "Bronze bar",
        "itemType": "Bronze bar",
        "itemRequiredLevel": 1,
        "itemValue": 1
      }
    },
    {
      "type": "miniRPG.Smeltable",
      "data": {
        "name": "Bronze bar",
        "requiredLevelToSmith": 1,
        "value": 1,
        "itemName": "Bronze bar",
        "itemType": "Bronze bar",
        "itemRequiredLevel": 1,
        "itemValue": 1
      }
    },
    {
      "type": "miniRPG.Smeltable",
      "data": {
        "name": "Bronze bar",
        "requiredLevelToSmith": 1,
        "value": 1,
        "itemName": "Bronze bar",
        "itemType": "Bronze bar",
        "itemRequiredLevel": 1,
        "itemValue": 1
      }
    },
    {
      "type": "miniRPG.Smeltable",
      "data": {
        "name": "Bronze bar",
        "requiredLevelToSmith": 1,
        "value": 1,
        "itemName": "Bronze bar",
        "itemType": "Bronze bar",
        "itemRequiredLevel": 1,
        "itemValue": 1
      }
    },
    {
      "type": "miniRPG.Smeltable",
      "data": {
        "name": "Bronze bar",
        "requiredLevelToSmith": 1,
        "value": 1,
        "itemName": "Bronze bar",
        "itemType": "Bronze bar",
        "itemRequiredLevel": 1,
        "itemValue": 1
      }
    },
    {
      "type": "miniRPG.Smeltable",
      "data": {
        "name": "Iron bar",
        "requiredLevelToSmith": 5,
        "value": 1,
        "itemName": "Iron bar",
        "itemType": "Iron bar",
        "itemRequiredLevel": 5,
        "itemValue": 1
      }
    },
    {
      "type": "miniRPG.Smeltable",
      "data": {
        "name": "Gold bar",
        "requiredLevelToSmith": 5,
        "value": 1,
        "itemName": "Gold bar",
        "itemType": "Gold bar",
        "itemRequiredLevel": 5,
        "itemValue": 1
      }
    },
    {
      "type": "miniRPG.Smeltable",
      "data": {
        "name": "Gold bar",
        "requiredLevelToSmith": 5,
        "value": 1,
        "itemName": "Gold bar",
        "itemType": "Gold bar",
        "itemRequiredLevel": 5,
        "itemValue": 1
      }
    },
    {
      "type": "miniRPG.Smeltable",
      "data": {
        "name": "Gold bar",
        "requiredLevelToSmith": 5,
        "value": 1,
        "itemName": "Gold bar",
        "itemType": "Gold bar",
        "itemRequiredLevel": 5,
        "itemValue": 1
      }
    },
    {
      "type": "miniRPG.Smeltable",
      "data": {
        "name": "Gold bar",
        "requiredLevelToSmith": 5,
        "value": 1,
        "itemName": "Gold bar",
        "itemType": "Gold bar",
        "itemRequiredLevel": 5,
        "itemValue": 1
      }
    },
    {
      "type": "miniRPG.Smeltable",
      "data": {
        "name": "Gold bar",
        "requiredLevelToSmith": 5,
        "value": 1,
        "itemName": "Gold bar",
        "itemType": "Gold bar",
        "itemRequiredLevel": 5,
        "itemValue": 1
      }
    },
    {
      "type": "miniRPG.Smeltable",
      "data": {
        "name": "Gold bar",
        "requiredLevelToSmith": 5,
        "value": 1,
        "itemName": "Gold bar",
        "itemType": "Gold bar",
        "itemRequiredLevel": 5,
        "itemValue": 1
      }
    },
    {
      "type": "miniRPG.Smeltable",
      "data": {
        "name": "Gold bar",
        "requiredLevelToSmith": 5,
        "value": 1,
        "itemName": "Gold bar",
        "itemType": "Gold bar",
        "itemRequiredLevel": 5,
        "itemValue": 1
      }
    },
    {
      "type": "miniRPG.Smeltable",
      "data": {
        "name": "Gold bar",
        "requiredLevelToSmith": 5,
        "value": 1,
        "itemName": "Gold bar",
        "itemType": "Gold bar",
        "itemRequiredLevel": 5,
        "itemValue": 1
      }
    },
    {
      "type": "miniRPG.Smeltable",
      "data": {
        "name": "Gold bar",
        "requiredLevelToSmith": 5,
        "value": 1,
        "itemName": "Gold bar",
        "itemType": "Gold bar",
        "itemRequiredLevel": 5,
        "itemValue": 1
      }
    },
    {
      "type": "miniRPG.Smeltable",
      "data": {
        "name": "Gold bar",
        "requiredLevelToSmith": 5,
        "value": 1,
        "itemName": "Gold bar",
        "itemType": "Gold bar",
        "itemRequiredLevel": 5,
        "itemValue": 1
      }
    },
    {
      "type": "miniRPG.Smeltable",
      "data": {
        "name": "Gold bar",
        "requiredLevelToSmith": 5,
        "value": 1,
        "itemName": "Gold bar",
        "itemType": "Gold bar",
        "itemRequiredLevel": 5,
        "itemValue": 1
      }
    },
    {
      "type": "miniRPG.Smeltable",
      "data": {
        "name": "Gold bar",
        "requiredLevelToSmith": 5,
        "value": 1,
        "itemName": "Gold bar",
        "itemType": "Gold bar",
        "itemRequiredLevel": 5,
        "itemValue": 1
      }
    },
    {
      "type": "miniRPG.Smeltable",
      "data": {
        "name": "Iron bar",
        "requiredLevelToSmith": 5,
        "value": 1,
        "itemName": "Iron bar",
        "itemType": "Iron bar",
        "itemRequiredLevel": 5,
        "itemValue": 1
      }
    },
    {
      "type": "miniRPG.Smeltable",
      "data": {
        "name": "Iron bar",
        "requiredLevelToSmith": 5,
        "value": 1,
        "itemName": "Iron bar",
        "itemType": "Iron bar",
        "itemRequiredLevel": 5,
        "itemValue": 1
      }
    },
    {
      "type": "miniRPG.Consumable",
      "data": {
        "healAmount": 111,
        "consumableValue": 0,
        "itemName": "Shrimp",
        "itemType": "Shrimp",
        "itemRequiredLevel": 1,
        "itemValue": 10
      }
    },
    {
      "type": "miniRPG.Consumable",
      "data": {
        "healAmount": 111,
        "consumableValue": 0,
        "itemName": "Shrimp",
        "itemType": "Shrimp",
        "itemRequiredLevel": 1,
        "itemValue": 10
      }
    },
    {
      "type": "miniRPG.Consumable",
      "data": {
        "healAmount": 111,
        "consumableValue": 0,
        "itemName": "Shrimp",
        "itemType": "Shrimp",
        "itemRequiredLevel": 1,
        "itemValue": 10
      }
    },
    {
      "type": "miniRPG.Consumable",
      "data": {
        "healAmount": 111,
        "consumableValue": 0,
        "itemName": "Shrimp",
        "itemType": "Shrimp",
        "itemRequiredLevel": 1,
        "itemValue": 10
      }
    },
    {
      "type": "miniRPG.Consumable",
      "data": {
        "healAmount": 111,
        "consumableValue": 0,
        "itemName": "Shrimp",
        "itemType": "Shrimp",
        "itemRequiredLevel": 1,
        "itemValue": 10
      }
    },
    {
      "type": "miniRPG.Consumable",
      "data": {
        "healAmount": 111,
        "consumableValue": 0,
        "itemName": "Shrimp",
        "itemType": "Shrimp",
        "itemRequiredLevel": 1,
        "itemValue": 10
      }
    },
    {
      "type": "miniRPG.Consumable",
      "data": {
        "healAmount": 111,
        "consumableValue": 0,
        "itemName": "Shrimp",
        "itemType": "Shrimp",
        "itemRequiredLevel": 1,
        "itemValue": 10
      }
    },
    {
      "type": "miniRPG.Consumable",
      "data": {
        "healAmount": 111,
        "consumableValue": 0,
        "itemName": "Shrimp",
        "itemType": "Shrimp",
        "itemRequiredLevel": 1,
        "itemValue": 10
      }
    },
    {
      "type": "miniRPG.Consumable",
      "data": {
        "healAmount": 111,
        "consumableValue": 0,
        "itemName": "Shrimp",
        "itemType": "Shrimp",
        "itemRequiredLevel": 1,
        "itemValue": 10
      }
    },
    {
      "type": "miniRPG.Consumable",
      "data": {
        "healAmount": 111,
        "consumableValue": 0,
        "itemName": "Shrimp",
        "itemType": "Shrimp",
        "itemRequiredLevel": 1,
        "itemValue": 10
      }
    },
    {
      "type": "miniRPG.Consumable",
      "data": {
        "healAmount": 111,
        "consumableValue": 0,
        "itemName": "Shrimp",
        "itemType": "Shrimp",
        "itemRequiredLevel": 1,
        "itemValue": 10
      }
    },
    {
      "type": "miniRPG.Consumable",
      "data": {
        "healAmount": 111,
        "consumableValue": 0,
        "itemName": "Shrimp",
        "itemType": "Shrimp",
        "itemRequiredLevel": 1,
        "itemValue": 10
      }
    },
    {
      "type": "miniRPG.Consumable",
      "data": {
        "healAmount": 111,
        "consumableValue": 0,
        "itemName": "Shrimp",
        "itemType": "Shrimp",
        "itemRequiredLevel": 1,
        "itemValue": 10
      }
    },
    {
      "type": "miniRPG.Consumable",
      "data": {
        "healAmount": 111,
        "consumableValue": 0,
        "itemName": "Shrimp",
        "itemType": "Shrimp",
        "itemRequiredLevel": 1,
        "itemValue": 10
      }
    },
    {
      "type": "miniRPG.Consumable",
      "data": {
        "healAmount": 111,
        "consumableValue": 0,
        "itemName": "Shrimp",
        "itemType": "Shrimp",
        "itemRequiredLevel": 1,
        "itemValue": 10
      }
    },
    {
      "type": "miniRPG.Consumable",
      "data": {
        "healAmount": 111,
        "consumableValue": 0,
        "itemName": "Shrimp",
        "itemType": "Shrimp",
        "itemRequiredLevel": 1,
        "itemValue": 10
      }
    },
    {
      "type": "miniRPG.Consumable",
      "data": {
        "healAmount": 111,
        "consumableValue": 0,
        "itemName": "Shrimp",
        "itemType": "Shrimp",
        "itemRequiredLevel": 1,
        "itemValue": 10
      }
    },
    {
      "type": "miniRPG.Consumable",
      "data": {
        "healAmount": 111,
        "consumableValue": 0,
        "itemName": "Shrimp",
        "itemType": "Shrimp",
        "itemRequiredLevel": 1,
        "itemValue": 10
      }
    },
    {
      "type": "miniRPG.Consumable",
      "data": {
        "healAmount": 111,
        "consumableValue": 0,
        "itemName": "Fish",
        "itemType": "Fish",
        "itemRequiredLevel": 1,
        "itemValue": 15
      }
    },
    {
      "type": "miniRPG.Consumable",
      "data": {
        "healAmount": 111,
        "consumableValue": 0,
        "itemName": "Fish",
        "itemType": "Fish",
        "itemRequiredLevel": 1,
        "itemValue": 15
      }
    },
    {
      "type": "miniRPG.Consumable",
      "data": {
        "healAmount": 111,
        "consumableValue": 0,
        "itemName": "Fish",
        "itemType": "Fish",
        "itemRequiredLevel": 1,
        "itemValue": 15
      }
    },
    {
      "type": "miniRPG.Consumable",
      "data": {
        "healAmount": 111,
        "consumableValue": 0,
        "itemName": "Fish",
        "itemType": "Fish",
        "itemRequiredLevel": 1,
        "itemValue": 15
      }
    },
    {
      "type": "miniRPG.Consumable",
      "data": {
        "healAmount": 111,
        "consumableValue": 0,
        "itemName": "Fish",
        "itemType": "Fish",
        "itemRequiredLevel": 1,
        "itemValue": 15
      }
    },
    {
      "type": "miniRPG.Consumable",
      "data": {
        "healAmount": 111,
        "consumableValue": 0,
        "itemName": "Fish",
        "itemType": "Fish",
        "itemRequiredLevel": 1,
        "itemValue": 15
      }
    },
    {
      "type": "miniRPG.Jewelry",
      "data": {
        "name": "Sapphire Ring",
        "hpBoost": 0,
        "attackBoost": 0,
        "defenseBoost": 3,
        "value": 50,
        "itemName": "Sapphire Ring",
        "itemType": "jewelry",
        "itemRequiredLevel": 1,
        "itemValue": 50
      }
    }
  ],
  "equippedItems": [
    {
      "type": "miniRPG.Weapon",
      "data": {
        "attackBoost": 3,
        "weaponRequiredLevel": 0,
        "weaponValue": 0,
        "itemName": "Bronze sword",
        "itemType": "sword",
        "itemRequiredLevel": 1,
        "itemValue": 50
      }
    },
    {
      "type": "miniRPG.Armor",
      "data": {
        "defenseBoost": 4,
        "armorRequiredLevel": 0,
        "armorValue": 0,
        "itemName": "Bronze helmet",
        "itemType": "helmet",
        "itemRequiredLevel": 1,
        "itemValue": 50
      }
    },
    {
      "type": "miniRPG.Armor",
      "data": {
        "defenseBoost": 4,
        "armorRequiredLevel": 0,
        "armorValue": 0,
        "itemName": "Bronze platelegs",
        "itemType": "platelegs",
        "itemRequiredLevel": 1,
        "itemValue": 50
      }
    },
    {
      "type": "miniRPG.Armor",
      "data": {
        "defenseBoost": 7,
        "armorRequiredLevel": 0,
        "armorValue": 0,
        "itemName": "Iron platebody",
        "itemType": "platebody",
        "itemRequiredLevel": 3,
        "itemValue": 100
      }
    },
    {
      "type": "miniRPG.Jewelry",
      "data": {
        "name": "Sapphire Ring",
        "hpBoost": 0,
        "attackBoost": 0,
        "defenseBoost": 3,
        "value": 50,
        "itemName": "Sapphire Ring",
        "itemType": "Sapphire Ring",
        "itemRequiredLevel": 1,
        "itemValue": 50
      }
    }
  ],
  "levelList": [
    {
      "xpList": [
        0,
        0,
        200,
        600,
        1200,
        2000,
        3050,
        4350,
        5950,
        7800,
        9950,
        12400,
        15150,
        18200,
        21600,
        25350,
        29400,
        33800,
        38550,
        43650,
        49100,
        54950,
        61150,
        67750,
        74700,
        82050,
        89800,
        97950,
        106500,
        115450,
        124800,
        2147483647
      ],
      "levelXp": 3106,
      "levelName": "Combat",
      "levelBeforeLevelingUp": 6
    },
    {
      "xpList": [
        0,
        0,
        200,
        600,
        1200,
        2000,
        3050,
        4350,
        5950,
        7800,
        9950,
        12400,
        15150,
        18200,
        21600,
        25350,
        29400,
        33800,
        38550,
        43650,
        49100,
        54950,
        61150,
        67750,
        74700,
        82050,
        89800,
        97950,
        106500,
        115450,
        124800,
        2147483647
      ],
      "levelXp": 5810,
      "levelName": "Mining",
      "levelBeforeLevelingUp": 7
    },
    {
      "xpList": [
        0,
        0,
        200,
        600,
        1200,
        2000,
        3050,
        4350,
        5950,
        7800,
        9950,
        12400,
        15150,
        18200,
        21600,
        25350,
        29400,
        33800,
        38550,
        43650,
        49100,
        54950,
        61150,
        67750,
        74700,
        82050,
        89800,
        97950,
        106500,
        115450,
        124800,
        2147483647
      ],
      "levelXp": 4510,
      "levelName": "Smithing",
      "levelBeforeLevelingUp": 7
    },
    {
      "xpList": [
        0,
        0,
        200,
        600,
        1200,
        2000,
        3050,
        4350,
        5950,
        7800,
        9950,
        12400,
        15150,
        18200,
        21600,
        25350,
        29400,
        33800,
        38550,
        43650,
        49100,
        54950,
        61150,
        67750,
        74700,
        82050,
        89800,
        97950,
        106500,
        115450,
        124800,
        2147483647
      ],
      "levelXp": 13375,
      "levelName": "Cooking",
      "levelBeforeLevelingUp": 11
    },
    {
      "xpList": [
        0,
        0,
        200,
        600,
        1200,
        2000,
        3050,
        4350,
        5950,
        7800,
        9950,
        12400,
        15150,
        18200,
        21600,
        25350,
        29400,
        33800,
        38550,
        43650,
        49100,
        54950,
        61150,
        67750,
        74700,
        82050,
        89800,
        97950,
        106500,
        115450,
        124800,
        2147483647
      ],
      "levelXp": 18080,
      "levelName": "Fishing",
      "levelBeforeLevelingUp": 12
    }
  ],
  "bankedItemList": []
}